{"assets/calLeftBtn.png":["assets/calLeftBtn.png"],"assets/calRightBtn.png":["assets/calRightBtn.png"],"assets/chart.png":["assets/chart.png"],"assets/coffee.svg":["assets/coffee.svg"],"assets/default.png":["assets/default.png"],"assets/dosomething.svg":["assets/dosomething.svg"],"assets/down_arrow.png":["assets/down_arrow.png"],"assets/error.png":["assets/error.png"],"assets/facebook.svg":["assets/facebook.svg"],"assets/finDo.png":["assets/finDo.png"],"assets/finInternet.png":["assets/finInternet.png"],"assets/finNot.png":["assets/finNot.png"],"assets/finPre.png":["assets/finPre.png"],"assets/finSmoke.png":["assets/finSmoke.png"],"assets/finSnack.png":["assets/finSnack.png"],"assets/finToilet.png":["assets/finToilet.png"],"assets/finWind.png":["assets/finWind.png"],"assets/fonts/Pretendard-Bold.otf":["assets/fonts/Pretendard-Bold.otf"],"assets/fonts/Pretendard-Medium.otf":["assets/fonts/Pretendard-Medium.otf"],"assets/fonts/Pretendard-Regular.otf":["assets/fonts/Pretendard-Regular.otf"],"assets/home.png":["assets/home.png"],"assets/insta.png":["assets/insta.png"],"assets/internet.svg":["assets/internet.svg"],"assets/kakao.png":["assets/kakao.png"],"assets/link.svg":["assets/link.svg"],"assets/logo.png":["assets/logo.png"],"assets/mainInternet.png":["assets/mainInternet.png"],"assets/mainInternet.svg":["assets/mainInternet.svg"],"assets/mainNot.png":["assets/mainNot.png"],"assets/mainNot.svg":["assets/mainNot.svg"],"assets/mainPrepare.png":["assets/mainPrepare.png"],"assets/mainPrepare.svg":["assets/mainPrepare.svg"],"assets/mainSmoke.png":["assets/mainSmoke.png"],"assets/mainSmoke.svg":["assets/mainSmoke.svg"],"assets/mainSnack.svg":["assets/mainSnack.svg"],"assets/mainSome.png":["assets/mainSome.png"],"assets/mainSome.svg":["assets/mainSome.svg"],"assets/mainToilet.png":["assets/mainToilet.png"],"assets/mainToilet.svg":["assets/mainToilet.svg"],"assets/mainWind.png":["assets/mainWind.png"],"assets/mainWind.svg":["assets/mainWind.svg"],"assets/nothing.svg":["assets/nothing.svg"],"assets/play.png":["assets/play.png"],"assets/play.svg":["assets/play.svg"],"assets/prepare.svg":["assets/prepare.svg"],"assets/settings.svg":["assets/settings.svg"],"assets/share.png":["assets/share.png"],"assets/smoke.svg":["assets/smoke.svg"],"assets/snacks.png":["assets/snacks.png"],"assets/stat.png":["assets/stat.png"],"assets/statistics.svg":["assets/statistics.svg"],"assets/stop.svg":["assets/stop.svg"],"assets/stopBtn.png":["assets/stopBtn.png"],"assets/team_logo.png":["assets/team_logo.png"],"assets/testRes.png":["assets/testRes.png"],"assets/toilet.svg":["assets/toilet.svg"],"assets/trash.png":["assets/trash.png"],"assets/twitter.svg":["assets/twitter.svg"],"assets/wind.svg":["assets/wind.svg"],"assets/x4do.png":["assets/x4do.png"],"assets/x4dores.png":["assets/x4dores.png"],"assets/x4internet.png":["assets/x4internet.png"],"assets/x4internetres.png":["assets/x4internetres.png"],"assets/x4not.png":["assets/x4not.png"],"assets/x4notres.png":["assets/x4notres.png"],"assets/x4prepare.png":["assets/x4prepare.png"],"assets/x4prepareres.png":["assets/x4prepareres.png"],"assets/x4set.png":["assets/x4set.png"],"assets/x4smoke.png":["assets/x4smoke.png"],"assets/x4smokeres.png":["assets/x4smokeres.png"],"assets/x4snack.png":["assets/x4snack.png"],"assets/x4snackres.png":["assets/x4snackres.png"],"assets/x4stat.png":["assets/x4stat.png"],"assets/x4toilet.png":["assets/x4toilet.png"],"assets/x4toiletres.png":["assets/x4toiletres.png"],"assets/x4wind.png":["assets/x4wind.png"],"assets/x4windres.png":["assets/x4windres.png"],"assets/x4zerores.png":["assets/x4zerores.png"],"assets/x8snack.png":["assets/x8snack.png"],"packages/cupertino_icons/assets/CupertinoIcons.ttf":["packages/cupertino_icons/assets/CupertinoIcons.ttf"],"packages/fluttertoast/assets/toastify.css":["packages/fluttertoast/assets/toastify.css"],"packages/fluttertoast/assets/toastify.js":["packages/fluttertoast/assets/toastify.js"]}